{
  "city": "nyc",
  "issued_local_std": "2026-05-05 12:00:00",
  "issued_pst": "2026-05-05 12:00:00",
  "n_signals": 18,
  "n_actionable": 15,
  "signals": [
    {
      "ticker": "KXHIGHNY-26MAY06-T74",
      "event_ticker": "KXHIGHNY-26MAY06",
      "series_ticker": "KXHIGHNY",
      "side_label": "HIGH",
      "day_D": "2026-05-05",
      "hours_to_settle": 12.0,
      "yes_sub_title": "75\u00b0 or above",
      "strike_type": "greater",
      "floor_strike": 74,
      "cap_strike": null,
      "yes_bid": 0.03,
      "yes_ask": 0.05,
      "spread": 0.020000000000000004,
      "model_prob_yes": 1.0,
      "meta_prob_yes": null,
      "p_final": 1.0,
      "model_median_temp_f": 78.04,
      "trade_side": "yes",
      "trade_cost": 0.05,
      "trade_ev_per_c": 0.94,
      "kelly_full": 1.0,
      "kelly_used": 0.05,
      "open_interest": null,
      "volume": null,
      "data_status": "candle"
    },
    {
      "ticker": "KXLOWTNYC-26MAY05-B58.5",
      "event_ticker": "KXLOWTNYC-26MAY05",
      "series_ticker": "KXLOWTNYC",
      "side_label": "LOW",
      "day_D": "2026-05-05",
      "hours_to_settle": 12.0,
      "yes_sub_title": "58\u00b0 to 59\u00b0",
      "strike_type": "between",
      "floor_strike": 58,
      "cap_strike": 59,
      "yes_bid": 0.99,
      "yes_ask": 1.0,
      "spread": 0.010000000000000009,
      "model_prob_yes": 0.4595,
      "meta_prob_yes": null,
      "p_final": 0.4595,
      "model_median_temp_f": 57.91,
      "trade_side": "no",
      "trade_cost": 0.010000000000000009,
      "trade_ev_per_c": 0.5204516276489778,
      "kelly_full": 0.5358,
      "kelly_used": 0.05,
      "open_interest": null,
      "volume": null,
      "data_status": "candle"
    },
    {
      "ticker": "KXHIGHNY-26MAY06-B69.5",
      "event_ticker": "KXHIGHNY-26MAY06",
      "series_ticker": "KXHIGHNY",
      "side_label": "HIGH",
      "day_D": "2026-05-05",
      "hours_to_settle": 12.0,
      "yes_sub_title": "69\u00b0 to 70\u00b0",
      "strike_type": "between",
      "floor_strike": 69,
      "cap_strike": 70,
      "yes_bid": 0.4,
      "yes_ask": 0.41,
      "spread": 0.009999999999999953,
      "model_prob_yes": 0.0,
      "meta_prob_yes": null,
      "p_final": 0.0,
      "model_median_temp_f": 78.04,
      "trade_side": "no",
      "trade_cost": 0.6,
      "trade_ev_per_c": 0.38320000000000004,
      "kelly_full": 1.0,
      "kelly_used": 0.05,
      "open_interest": null,
      "volume": null,
      "data_status": "candle"
    },
    {
      "ticker": "KXLOWTNYC-26MAY06-T56",
      "event_ticker": "KXLOWTNYC-26MAY06",
      "series_ticker": "KXLOWTNYC",
      "side_label": "LOW",
      "day_D": "2026-05-06",
      "hours_to_settle": 36.0,
      "yes_sub_title": "55\u00b0 or below",
      "strike_type": "less",
      "floor_strike": null,
      "cap_strike": 56,
      "yes_bid": 0.09,
      "yes_ask": 0.1,
      "spread": 0.010000000000000009,
      "model_prob_yes": 0.4643,
      "meta_prob_yes": null,
      "p_final": 0.4643,
      "model_median_temp_f": 56.02,
      "trade_side": "yes",
      "trade_cost": 0.1,
      "trade_ev_per_c": 0.35425750980782045,
      "kelly_full": 0.4047,
      "kelly_used": 0.05,
      "open_interest": null,
      "volume": null,
      "data_status": "candle"
    },
    {
      "ticker": "KXHIGHNY-26MAY06-B71.5",
      "event_ticker": "KXHIGHNY-26MAY06",
      "series_ticker": "KXHIGHNY",
      "side_label": "HIGH",
      "day_D": "2026-05-05",
      "hours_to_settle": 12.0,
      "yes_sub_title": "71\u00b0 to 72\u00b0",
      "strike_type": "between",
      "floor_strike": 71,
      "cap_strike": 72,
      "yes_bid": 0.31,
      "yes_ask": 0.33,
      "spread": 0.020000000000000018,
      "model_prob_yes": 0.0,
      "meta_prob_yes": null,
      "p_final": 0.0,
      "model_median_temp_f": 78.04,
      "trade_side": "no",
      "trade_cost": 0.69,
      "trade_ev_per_c": 0.29502700000000004,
      "kelly_full": 1.0,
      "kelly_used": 0.05,
      "open_interest": null,
      "volume": null,
      "data_status": "candle"
    },
    {
      "ticker": "KXLOWTNYC-26MAY05-B56.5",
      "event_ticker": "KXLOWTNYC-26MAY05",
      "series_ticker": "KXLOWTNYC",
      "side_label": "LOW",
      "day_D": "2026-05-05",
      "hours_to_settle": 12.0,
      "yes_sub_title": "56\u00b0 to 57\u00b0",
      "strike_type": "between",
      "floor_strike": 56,
      "cap_strike": 57,
      "yes_bid": 0.0,
      "yes_ask": 0.04,
      "spread": 0.04,
      "model_prob_yes": 0.2257,
      "meta_prob_yes": null,
      "p_final": 0.2257,
      "model_median_temp_f": 57.91,
      "trade_side": "yes",
      "trade_cost": 0.04,
      "trade_ev_per_c": 0.17566294932630666,
      "kelly_full": 0.1934,
      "kelly_used": 0.0483,
      "open_interest": null,
      "volume": null,
      "data_status": "candle"
    },
    {
      "ticker": "KXLOWTNYC-26MAY06-B58.5",
      "event_ticker": "KXLOWTNYC-26MAY06",
      "series_ticker": "KXLOWTNYC",
      "side_label": "LOW",
      "day_D": "2026-05-06",
      "hours_to_settle": 36.0,
      "yes_sub_title": "58\u00b0 to 59\u00b0",
      "strike_type": "between",
      "floor_strike": 58,
      "cap_strike": 59,
      "yes_bid": 0.22,
      "yes_ask": 0.26,
      "spread": 0.04000000000000001,
      "model_prob_yes": 0.082,
      "meta_prob_yes": null,
      "p_final": 0.082,
      "model_median_temp_f": 56.02,
      "trade_side": "no",
      "trade_cost": 0.78,
      "trade_ev_per_c": 0.125938473641429,
      "kelly_full": 0.627,
      "kelly_used": 0.05,
      "open_interest": null,
      "volume": null,
      "data_status": "candle"
    },
    {
      "ticker": "KXHIGHNY-26MAY06-B67.5",
      "event_ticker": "KXHIGHNY-26MAY06",
      "series_ticker": "KXHIGHNY",
      "side_label": "HIGH",
      "day_D": "2026-05-05",
      "hours_to_settle": 12.0,
      "yes_sub_title": "67\u00b0 to 68\u00b0",
      "strike_type": "between",
      "floor_strike": 67,
      "cap_strike": 68,
      "yes_bid": 0.13,
      "yes_ask": 0.14,
      "spread": 0.010000000000000009,
      "model_prob_yes": 0.0,
      "meta_prob_yes": null,
      "p_final": 0.0,
      "model_median_temp_f": 78.04,
      "trade_side": "no",
      "trade_cost": 0.87,
      "trade_ev_per_c": 0.12000000000000001,
      "kelly_full": 1.0,
      "kelly_used": 0.05,
      "open_interest": null,
      "volume": null,
      "data_status": "candle"
    },
    {
      "ticker": "KXLOWTNYC-26MAY06-B60.5",
      "event_ticker": "KXLOWTNYC-26MAY06",
      "series_ticker": "KXLOWTNYC",
      "side_label": "LOW",
      "day_D": "2026-05-06",
      "hours_to_settle": 36.0,
      "yes_sub_title": "60\u00b0 to 61\u00b0",
      "strike_type": "between",
      "floor_strike": 60,
      "cap_strike": 61,
      "yes_bid": 0.19,
      "yes_ask": 0.26,
      "spread": 0.07,
      "model_prob_yes": 0.0692,
      "meta_prob_yes": null,
      "p_final": 0.0692,
      "model_median_temp_f": 56.02,
      "trade_side": "no",
      "trade_cost": 0.81,
      "trade_ev_per_c": 0.11000961474878326,
      "kelly_full": 0.6357,
      "kelly_used": 0.05,
      "open_interest": null,
      "volume": null,
      "data_status": "candle"
    },
    {
      "ticker": "KXLOWTNYC-26MAY05-B52.5",
      "event_ticker": "KXLOWTNYC-26MAY05",
      "series_ticker": "KXLOWTNYC",
      "side_label": "LOW",
      "day_D": "2026-05-05",
      "hours_to_settle": 12.0,
      "yes_sub_title": "52\u00b0 to 53\u00b0",
      "strike_type": "between",
      "floor_strike": 52,
      "cap_strike": 53,
      "yes_bid": 0.0,
      "yes_ask": 0.01,
      "spread": 0.01,
      "model_prob_yes": 0.1098,
      "meta_prob_yes": null,
      "p_final": 0.1098,
      "model_median_temp_f": 57.91,
      "trade_side": "yes",
      "trade_cost": 0.01,
      "trade_ev_per_c": 0.08975430909771102,
      "kelly_full": 0.1008,
      "kelly_used": 0.0252,
      "open_interest": null,
      "volume": null,
      "data_status": "candle"
    },
    {
      "ticker": "KXLOWTNYC-26MAY05-B54.5",
      "event_ticker": "KXLOWTNYC-26MAY05",
      "series_ticker": "KXLOWTNYC",
      "side_label": "LOW",
      "day_D": "2026-05-05",
      "hours_to_settle": 12.0,
      "yes_sub_title": "54\u00b0 to 55\u00b0",
      "strike_type": "between",
      "floor_strike": 54,
      "cap_strike": 55,
      "yes_bid": 0.0,
      "yes_ask": 0.01,
      "spread": 0.01,
      "model_prob_yes": 0.1073,
      "meta_prob_yes": null,
      "p_final": 0.1073,
      "model_median_temp_f": 57.91,
      "trade_side": "yes",
      "trade_cost": 0.01,
      "trade_ev_per_c": 0.08725526995104764,
      "kelly_full": 0.0982,
      "kelly_used": 0.0246,
      "open_interest": null,
      "volume": null,
      "data_status": "candle"
    },
    {
      "ticker": "KXLOWTNYC-26MAY05-T59",
      "event_ticker": "KXLOWTNYC-26MAY05",
      "series_ticker": "KXLOWTNYC",
      "side_label": "LOW",
      "day_D": "2026-05-05",
      "hours_to_settle": 12.0,
      "yes_sub_title": "60\u00b0 or above",
      "strike_type": "greater",
      "floor_strike": 59,
      "cap_strike": null,
      "yes_bid": 0.0,
      "yes_ask": 0.01,
      "spread": 0.01,
      "model_prob_yes": 0.0978,
      "meta_prob_yes": null,
      "p_final": 0.0978,
      "model_median_temp_f": 57.91,
      "trade_side": "yes",
      "trade_cost": 0.01,
      "trade_ev_per_c": 0.0777790992739125,
      "kelly_full": 0.0887,
      "kelly_used": 0.0222,
      "open_interest": null,
      "volume": null,
      "data_status": "candle"
    },
    {
      "ticker": "KXLOWTNYC-26MAY06-B62.5",
      "event_ticker": "KXLOWTNYC-26MAY06",
      "series_ticker": "KXLOWTNYC",
      "side_label": "LOW",
      "day_D": "2026-05-06",
      "hours_to_settle": 36.0,
      "yes_sub_title": "62\u00b0 to 63\u00b0",
      "strike_type": "between",
      "floor_strike": 62,
      "cap_strike": 63,
      "yes_bid": 0.12,
      "yes_ask": 0.16,
      "spread": 0.04000000000000001,
      "model_prob_yes": 0.048,
      "meta_prob_yes": null,
      "p_final": 0.048,
      "model_median_temp_f": 56.02,
      "trade_side": "no",
      "trade_cost": 0.88,
      "trade_ev_per_c": 0.06198111769524673,
      "kelly_full": 0.5998,
      "kelly_used": 0.05,
      "open_interest": null,
      "volume": null,
      "data_status": "candle"
    },
    {
      "ticker": "KXHIGHNY-26MAY06-B73.5",
      "event_ticker": "KXHIGHNY-26MAY06",
      "series_ticker": "KXHIGHNY",
      "side_label": "HIGH",
      "day_D": "2026-05-05",
      "hours_to_settle": 12.0,
      "yes_sub_title": "73\u00b0 to 74\u00b0",
      "strike_type": "between",
      "floor_strike": 73,
      "cap_strike": 74,
      "yes_bid": 0.06,
      "yes_ask": 0.08,
      "spread": 0.020000000000000004,
      "model_prob_yes": 0.0,
      "meta_prob_yes": null,
      "p_final": 0.0,
      "model_median_temp_f": 78.04,
      "trade_side": "no",
      "trade_cost": 0.94,
      "trade_ev_per_c": 0.05000000000000005,
      "kelly_full": 1.0,
      "kelly_used": 0.05,
      "open_interest": null,
      "volume": null,
      "data_status": "candle"
    },
    {
      "ticker": "KXHIGHNY-26MAY06-T67",
      "event_ticker": "KXHIGHNY-26MAY06",
      "series_ticker": "KXHIGHNY",
      "side_label": "HIGH",
      "day_D": "2026-05-05",
      "hours_to_settle": 12.0,
      "yes_sub_title": "66\u00b0 or below",
      "strike_type": "less",
      "floor_strike": null,
      "cap_strike": 67,
      "yes_bid": 0.04,
      "yes_ask": 0.07,
      "spread": 0.030000000000000006,
      "model_prob_yes": 0.0,
      "meta_prob_yes": null,
      "p_final": 0.0,
      "model_median_temp_f": 78.04,
      "trade_side": "no",
      "trade_cost": 0.96,
      "trade_ev_per_c": 0.030000000000000034,
      "kelly_full": 1.0,
      "kelly_used": 0.05,
      "open_interest": null,
      "volume": null,
      "data_status": "candle"
    },
    {
      "ticker": "KXLOWTNYC-26MAY06-B56.5",
      "event_ticker": "KXLOWTNYC-26MAY06",
      "series_ticker": "KXLOWTNYC",
      "side_label": "LOW",
      "day_D": "2026-05-06",
      "hours_to_settle": 36.0,
      "yes_sub_title": "56\u00b0 to 57\u00b0",
      "strike_type": "between",
      "floor_strike": 56,
      "cap_strike": 57,
      "yes_bid": 0.24,
      "yes_ask": 0.28,
      "spread": 0.040000000000000036,
      "model_prob_yes": 0.2693,
      "meta_prob_yes": null,
      "p_final": 0.2693,
      "model_median_temp_f": 56.02,
      "trade_side": null,
      "trade_cost": null,
      "trade_ev_per_c": null,
      "kelly_full": 0.0,
      "kelly_used": 0.0,
      "open_interest": null,
      "volume": null,
      "data_status": "candle"
    },
    {
      "ticker": "KXLOWTNYC-26MAY06-T63",
      "event_ticker": "KXLOWTNYC-26MAY06",
      "series_ticker": "KXLOWTNYC",
      "side_label": "LOW",
      "day_D": "2026-05-06",
      "hours_to_settle": 36.0,
      "yes_sub_title": "64\u00b0 or above",
      "strike_type": "greater",
      "floor_strike": 63,
      "cap_strike": null,
      "yes_bid": 0.02,
      "yes_ask": 0.04,
      "spread": 0.02,
      "model_prob_yes": 0.0671,
      "meta_prob_yes": null,
      "p_final": 0.0671,
      "model_median_temp_f": 56.02,
      "trade_side": null,
      "trade_cost": null,
      "trade_ev_per_c": null,
      "kelly_full": 0.0,
      "kelly_used": 0.0,
      "open_interest": null,
      "volume": null,
      "data_status": "candle"
    },
    {
      "ticker": "KXLOWTNYC-26MAY05-T52",
      "event_ticker": "KXLOWTNYC-26MAY05",
      "series_ticker": "KXLOWTNYC",
      "side_label": "LOW",
      "day_D": "2026-05-05",
      "hours_to_settle": 12.0,
      "yes_sub_title": "51\u00b0 or below",
      "strike_type": "less",
      "floor_strike": null,
      "cap_strike": 52,
      "yes_bid": 0.0,
      "yes_ask": 0.01,
      "spread": 0.01,
      "model_prob_yes": 0.0,
      "meta_prob_yes": null,
      "p_final": 0.0,
      "model_median_temp_f": 57.91,
      "trade_side": null,
      "trade_cost": null,
      "trade_ev_per_c": null,
      "kelly_full": 0.0,
      "kelly_used": 0.0,
      "open_interest": null,
      "volume": null,
      "data_status": "candle"
    }
  ]
}